{
  "openapi": "3.0.0",
  "info": {
    "version": "3.0.0",
    "title": "Contact API Documentation",
    "description": "API Documentation for Project"
  },
  "servers": [
    {
      "url": "http://localhost:8000",
      "description": "API Description."
    },
    {
      "url": "https://web-servicescse341.onrender.com",
      "description": "API Description."
    }
  ],
  "paths": {
    "/api-docs": {
      "get": {
        "description": "",
        "responses": {
          "default": {
            "description": ""
          }
        }
      }
    },
    "/getAll": {
      "get": {
        "description": "",
        "responses": {
          "200": {
            "description": "OK"
          }
        }
      }
    },
    "/getContact/{id}": {
      "get": {
        "description": "",
        "parameters": [
          {
            "name": "id",
            "in": "path",
            "required": true,
            "schema": {
              "type": "string"
            }
          }
        ],
        "responses": {
          "200": {
            "description": "OK"
          }
        }
      }
    },
    "/deleteContact/{id}": {
      "delete": {
        "description": "",
        "parameters": [
          {
            "name": "id",
            "in": "path",
            "required": true,
            "schema": {
              "type": "string"
            }
          }
        ],
        "responses": {
          "200": {
            "description": "OK"
          }
        }
      }
    },
    "/newContact": {
      "post": {
        "description": "",
        "responses": {
          "200": {
            "description": "OK"
          }
        },
        "requestBody": {
          "content": {
            "application/json": {
              "schema": {
                "type": "object",
                "properties": {
                  "firstname": {
                    "example": "any"
                  },
                  "lastname": {
                    "example": "any"
                  },
                  "email": {
                    "example": "any"
                  },
                  "favouriteColor": {
                    "example": "any"
                  },
                  "birthday": {
                    "example": "any"
                  }
                }
              }
            }
          }
        }
      }
    },
    "/updateContact/{id}": {
      "put": {
        "description": "",
        "parameters": [
          {
            "name": "id",
            "in": "path",
            "required": true,
            "schema": {
              "type": "string"
            }
          }
        ],
        "responses": {
          "200": {
            "description": "OK"
          }
        },
        "requestBody": {
          "content": {
            "application/json": {
              "schema": {
                "type": "object",
                "properties": {
                  "firstname": {
                    "example": "any"
                  },
                  "lastname": {
                    "example": "any"
                  },
                  "email": {
                    "example": "any"
                  },
                  "favouriteColor": {
                    "example": "any"
                  },
                  "birthday": {
                    "example": "any"
                  }
                }
              }
            }
          }
        }
      }
    }
  }
}
